[
    {
        "Id": 1,
        "IsIgnore": null,
        "Memo": "通常_3体",
        "BattleParameterChangeInfos": [
            {
                "BattleParameterType": 1,
                "ChangeParameterType": 2,
                "Value": 1000.0
            },
            {
                "BattleParameterType": 2,
                "ChangeParameterType": 2,
                "Value": 1000.0
            }
        ],
        "ConditionType": 0,
        "Phase": 1
    },
    {
        "Id": 2,
        "IsIgnore": null,
        "Memo": "通常_3+2体",
        "BattleParameterChangeInfos": [
            {
                "BattleParameterType": 1,
                "ChangeParameterType": 2,
                "Value": 1500.0
            },
            {
                "BattleParameterType": 2,
                "ChangeParameterType": 2,
                "Value": 1500.0
            }
        ],
        "ConditionType": 0,
        "Phase": 2
    },
    {
        "Id": 3,
        "IsIgnore": null,
        "Memo": "通常_4体",
        "BattleParameterChangeInfos": [
            {
                "BattleParameterType": 1,
                "ChangeParameterType": 2,
                "Value": 2000.0
            },
            {
                "BattleParameterType": 2,
                "ChangeParameterType": 2,
                "Value": 1500.0
            }
        ],
        "ConditionType": 0,
        "Phase": 3
    },
    {
        "Id": 4,
        "IsIgnore": null,
        "Memo": "通常_5体",
        "BattleParameterChangeInfos": [
            {
                "BattleParameterType": 1,
                "ChangeParameterType": 2,
                "Value": 2500.0
            },
            {
                "BattleParameterType": 2,
                "ChangeParameterType": 2,
                "Value": 2500.0
            }
        ],
        "ConditionType": 0,
        "Phase": 4
    },
    {
        "Id": 5,
        "IsIgnore": null,
        "Memo": "冥_1体",
        "BattleParameterChangeInfos": [
            {
                "BattleParameterType": 13,
                "ChangeParameterType": 2,
                "Value": 2500.0
            }
        ],
        "ConditionType": 1,
        "Phase": 1
    },
    {
        "Id": 6,
        "IsIgnore": null,
        "Memo": "冥_2体",
        "BattleParameterChangeInfos": [
            {
                "BattleParameterType": 18,
                "ChangeParameterType": 1,
                "Value": 500.0
            }
        ],
        "ConditionType": 1,
        "Phase": 2
    },
    {
        "Id": 7,
        "IsIgnore": null,
        "Memo": "冥_3体",
        "BattleParameterChangeInfos": [
            {
                "BattleParameterType": 12,
                "ChangeParameterType": 1,
                "Value": 1000.0
            }
        ],
        "ConditionType": 1,
        "Phase": 3
    },
    {
        "Id": 8,
        "IsIgnore": null,
        "Memo": "冥_4体",
        "BattleParameterChangeInfos": [
            {
                "BattleParameterType": 17,
                "ChangeParameterType": 1,
                "Value": 1000.0
            }
        ],
        "ConditionType": 1,
        "Phase": 4
    },
    {
        "Id": 9,
        "IsIgnore": null,
        "Memo": "冥_5体",
        "BattleParameterChangeInfos": [
            {
                "BattleParameterType": 9,
                "ChangeParameterType": 1,
                "Value": 3000.0
            }
        ],
        "ConditionType": 1,
        "Phase": 5
    }
]