[
    {
        "Id": 1,
        "IsIgnore": null,
        "Memo": null,
        "CharacterIdList": [
            2,
            3,
            4,
            6,
            5,
            7,
            8,
            10,
            12,
            13,
            14,
            15,
            16,
            17,
            18,
            20,
            22,
            23,
            24,
            25,
            26,
            27,
            28,
            29,
            32,
            33,
            34,
            35,
            36,
            37,
            38,
            39
        ],
        "GachaSelectListType": 1,
        "NewCharacterIdList": null,
        "OrderNumber": 0,
        "StartTimeFixJST": "2020-01-01 00:00:00",
        "EndTimeFixJST": "2100-01-01 00:00:00"
    },
    {
        "Id": 2,
        "IsIgnore": null,
        "Memo": null,
        "CharacterIdList": [
            5,
            6,
            7,
            8,
            10,
            15,
            16,
            17,
            18,
            20,
            25,
            26,
            27,
            28,
            29,
            35,
            36,
            37,
            38,
            39,
            41,
            46
        ],
        "GachaSelectListType": 2,
        "NewCharacterIdList": null,
        "OrderNumber": 0,
        "StartTimeFixJST": "2020-01-01 00:00:00",
        "EndTimeFixJST": "2100-01-01 00:00:00"
    },
    {
        "Id": 3,
        "IsIgnore": null,
        "Memo": null,
        "CharacterIdList": [
            49,
            5,
            6,
            7,
            8,
            10,
            15,
            16,
            17,
            18,
            20,
            25,
            26,
            27,
            28,
            29,
            35,
            36,
            37,
            38,
            39,
            41,
            46
        ],
        "GachaSelectListType": 2,
        "NewCharacterIdList": [
            49
        ],
        "OrderNumber": 1,
        "StartTimeFixJST": "2023-02-28 17:30:00",
        "EndTimeFixJST": "2023-03-16 14:29:59"
    },
    {
        "Id": 4,
        "IsIgnore": null,
        "Memo": null,
        "CharacterIdList": [
            53,
            5,
            6,
            7,
            8,
            10,
            15,
            16,
            17,
            18,
            20,
            25,
            26,
            27,
            28,
            29,
            35,
            36,
            37,
            38,
            39,
            41,
            46
        ],
        "GachaSelectListType": 2,
        "NewCharacterIdList": [
            53
        ],
        "OrderNumber": 2,
        "StartTimeFixJST": "2023-03-16 17:30:00",
        "EndTimeFixJST": "2023-03-31 14:29:59"
    },
    {
        "Id": 5,
        "IsIgnore": null,
        "Memo": null,
        "CharacterIdList": [
            53,
            42,
            5,
            6,
            7,
            8,
            10,
            15,
            16,
            17,
            18,
            20,
            25,
            26,
            27,
            28,
            29,
            35,
            36,
            37,
            38,
            39,
            41,
            46
        ],
        "GachaSelectListType": 2,
        "NewCharacterIdList": [
            42,
            53
        ],
        "OrderNumber": 3,
        "StartTimeFixJST": "2023-03-23 17:30:00",
        "EndTimeFixJST": "2023-04-07 14:29:59"
    },
    {
        "Id": 6,
        "IsIgnore": null,
        "Memo": null,
        "CharacterIdList": [
            55,
            42,
            5,
            6,
            7,
            8,
            10,
            15,
            16,
            17,
            18,
            20,
            25,
            26,
            27,
            28,
            29,
            35,
            36,
            37,
            38,
            39,
            41,
            46
        ],
        "GachaSelectListType": 2,
        "NewCharacterIdList": [
            42,
            55
        ],
        "OrderNumber": 4,
        "StartTimeFixJST": "2023-03-31 17:30:00",
        "EndTimeFixJST": "2023-04-07 14:29:59"
    },
    {
        "Id": 7,
        "IsIgnore": null,
        "Memo": null,
        "CharacterIdList": [
            55,
            5,
            6,
            7,
            8,
            10,
            15,
            16,
            17,
            18,
            20,
            25,
            26,
            27,
            28,
            29,
            35,
            36,
            37,
            38,
            39,
            41,
            46
        ],
        "GachaSelectListType": 2,
        "NewCharacterIdList": [
            55
        ],
        "OrderNumber": 5,
        "StartTimeFixJST": "2023-04-07 14:30:00",
        "EndTimeFixJST": "2023-04-14 14:29:59"
    },
    {
        "Id": 8,
        "IsIgnore": null,
        "Memo": null,
        "CharacterIdList": [
            54,
            5,
            6,
            7,
            8,
            10,
            15,
            16,
            17,
            18,
            20,
            25,
            26,
            27,
            28,
            29,
            35,
            36,
            37,
            38,
            39,
            41,
            46
        ],
        "GachaSelectListType": 2,
        "NewCharacterIdList": [
            54
        ],
        "OrderNumber": 6,
        "StartTimeFixJST": "2023-04-14 17:30:00",
        "EndTimeFixJST": "2023-04-28 14:29:59"
    },
    {
        "Id": 9,
        "IsIgnore": null,
        "Memo": null,
        "CharacterIdList": [
            54,
            19,
            5,
            6,
            7,
            8,
            10,
            15,
            16,
            17,
            18,
            20,
            25,
            26,
            27,
            28,
            29,
            35,
            36,
            37,
            38,
            39,
            41,
            46
        ],
        "GachaSelectListType": 2,
        "NewCharacterIdList": [
            54,
            19
        ],
        "OrderNumber": 7,
        "StartTimeFixJST": "2023-04-21 14:30:00",
        "EndTimeFixJST": "2023-04-28 14:29:59"
    },
    {
        "Id": 10,
        "IsIgnore": null,
        "Memo": "ルサールカ・ベル",
        "CharacterIdList": [
            44,
            19,
            5,
            6,
            7,
            8,
            10,
            15,
            16,
            17,
            18,
            20,
            25,
            26,
            27,
            28,
            29,
            35,
            36,
            37,
            38,
            39,
            41,
            46
        ],
        "GachaSelectListType": 2,
        "NewCharacterIdList": [
            44,
            19
        ],
        "OrderNumber": 8,
        "StartTimeFixJST": "2023-04-28 17:30:00",
        "EndTimeFixJST": "2023-05-08 14:29:59"
    },
    {
        "Id": 11,
        "IsIgnore": null,
        "Memo": "ルサールカのみ",
        "CharacterIdList": [
            44,
            5,
            6,
            7,
            8,
            10,
            15,
            16,
            17,
            18,
            20,
            25,
            26,
            27,
            28,
            29,
            35,
            36,
            37,
            38,
            39,
            41,
            46
        ],
        "GachaSelectListType": 2,
        "NewCharacterIdList": [
            44
        ],
        "OrderNumber": 9,
        "StartTimeFixJST": "2023-05-08 14:30:00",
        "EndTimeFixJST": "2023-05-15 14:29:59"
    },
    {
        "Id": 12,
        "IsIgnore": null,
        "Memo": "シヴィのみ",
        "CharacterIdList": [
            52,
            5,
            6,
            7,
            8,
            10,
            15,
            16,
            17,
            18,
            20,
            25,
            26,
            27,
            28,
            29,
            35,
            36,
            37,
            38,
            39,
            41,
            46
        ],
        "GachaSelectListType": 2,
        "NewCharacterIdList": [
            52
        ],
        "OrderNumber": 10,
        "StartTimeFixJST": "2023-05-15 16:30:00",
        "EndTimeFixJST": "2023-05-31 14:29:59"
    },
    {
        "Id": 13,
        "IsIgnore": null,
        "Memo": "シヴィ・ルーク復刻",
        "CharacterIdList": [
            52,
            30,
            5,
            6,
            7,
            8,
            10,
            15,
            16,
            17,
            18,
            20,
            25,
            26,
            27,
            28,
            29,
            35,
            36,
            37,
            38,
            39,
            41,
            46
        ],
        "GachaSelectListType": 2,
        "NewCharacterIdList": [
            52,
            30
        ],
        "OrderNumber": 11,
        "StartTimeFixJST": "2023-05-22 14:30:00",
        "EndTimeFixJST": "2023-05-31 14:29:59"
    },
    {
        "Id": 14,
        "IsIgnore": null,
        "Memo": "アーティ・ルーク復刻(上書き)",
        "CharacterIdList": [
            58,
            30,
            5,
            6,
            7,
            8,
            10,
            15,
            16,
            17,
            18,
            20,
            25,
            26,
            27,
            28,
            29,
            35,
            36,
            37,
            38,
            39,
            41,
            46
        ],
        "GachaSelectListType": 2,
        "NewCharacterIdList": [
            58,
            30
        ],
        "OrderNumber": 12,
        "StartTimeFixJST": "2023-05-31 17:30:00",
        "EndTimeFixJST": "2023-06-07 14:29:59"
    },
    {
        "Id": 15,
        "IsIgnore": null,
        "Memo": "アーティ",
        "CharacterIdList": [
            58,
            5,
            6,
            7,
            8,
            10,
            15,
            16,
            17,
            18,
            20,
            25,
            26,
            27,
            28,
            29,
            35,
            36,
            37,
            38,
            39,
            41,
            46
        ],
        "GachaSelectListType": 2,
        "NewCharacterIdList": [
            58
        ],
        "OrderNumber": 13,
        "StartTimeFixJST": "2023-06-07 14:30:00",
        "EndTimeFixJST": "2023-06-14 14:29:59"
    },
    {
        "Id": 16,
        "IsIgnore": null,
        "Memo": "リシェス",
        "CharacterIdList": [
            67,
            5,
            6,
            7,
            8,
            10,
            15,
            16,
            17,
            18,
            20,
            25,
            26,
            27,
            28,
            29,
            35,
            36,
            37,
            38,
            39,
            41,
            46
        ],
        "GachaSelectListType": 2,
        "NewCharacterIdList": [
            67
        ],
        "OrderNumber": 14,
        "StartTimeFixJST": "2023-06-14 16:30:00",
        "EndTimeFixJST": "2023-06-21 14:29:59"
    },
    {
        "Id": 17,
        "IsIgnore": null,
        "Memo": "リシェス・ウィーラ(0621切替用)",
        "CharacterIdList": [
            67,
            53,
            5,
            6,
            7,
            8,
            10,
            15,
            16,
            17,
            18,
            20,
            25,
            26,
            27,
            28,
            29,
            35,
            36,
            37,
            38,
            39,
            41,
            46
        ],
        "GachaSelectListType": 2,
        "NewCharacterIdList": [
            67,
            53
        ],
        "OrderNumber": 15,
        "StartTimeFixJST": "2023-06-21 14:30:00",
        "EndTimeFixJST": "2023-06-30 14:29:59"
    },
    {
        "Id": 18,
        "IsIgnore": null,
        "Memo": "水着サブリナ・ウィーラ(0630切替用)",
        "CharacterIdList": [
            70,
            53,
            5,
            6,
            7,
            8,
            10,
            15,
            16,
            17,
            18,
            20,
            25,
            26,
            27,
            28,
            29,
            35,
            36,
            37,
            38,
            39,
            41,
            46
        ],
        "GachaSelectListType": 2,
        "NewCharacterIdList": [
            70,
            53
        ],
        "OrderNumber": 16,
        "StartTimeFixJST": "2023-06-30 16:30:00",
        "EndTimeFixJST": "2023-07-07 14:29:59"
    },
    {
        "Id": 19,
        "IsIgnore": null,
        "Memo": "水着サブリナ・ヴァルリーデ追加(0707切替用)",
        "CharacterIdList": [
            70,
            47,
            5,
            6,
            7,
            8,
            10,
            15,
            16,
            17,
            18,
            20,
            25,
            26,
            27,
            28,
            29,
            35,
            36,
            37,
            38,
            39,
            41,
            46
        ],
        "GachaSelectListType": 2,
        "NewCharacterIdList": [
            70,
            47
        ],
        "OrderNumber": 17,
        "StartTimeFixJST": "2023-07-07 14:30:00",
        "EndTimeFixJST": "2023-07-13 14:29:59"
    },
    {
        "Id": 20,
        "IsIgnore": null,
        "Memo": "水着モーザ・ヴァルリーデ(0713切替用)",
        "CharacterIdList": [
            71,
            47,
            5,
            6,
            7,
            8,
            10,
            15,
            16,
            17,
            18,
            20,
            25,
            26,
            27,
            28,
            29,
            35,
            36,
            37,
            38,
            39,
            41,
            46
        ],
        "GachaSelectListType": 2,
        "NewCharacterIdList": [
            71,
            47
        ],
        "OrderNumber": 18,
        "StartTimeFixJST": "2023-07-13 17:30:00",
        "EndTimeFixJST": "2023-07-24 14:29:59"
    },
    {
        "Id": 21,
        "IsIgnore": null,
        "Memo": "水着モーザ・ヴァルリーデなし(0724切替用)",
        "CharacterIdList": [
            71,
            5,
            6,
            7,
            8,
            10,
            15,
            16,
            17,
            18,
            20,
            25,
            26,
            27,
            28,
            29,
            35,
            36,
            37,
            38,
            39,
            41,
            46
        ],
        "GachaSelectListType": 2,
        "NewCharacterIdList": [
            71
        ],
        "OrderNumber": 19,
        "StartTimeFixJST": "2023-07-24 14:30:00",
        "EndTimeFixJST": "2023-07-31 14:29:59"
    }
]