{
    "MasterBookInfoMap": {
        "AchieveRankingRewardMB": {
            "Hash": "df700cdbeb55e910a2c863276e425107",
            "Name": "AchieveRankingRewardMB",
            "Size": 68960
        },
        "ActiveSkillMB": {
            "Hash": "031c2b56f8e1d9a32d46879cc6da498c",
            "Name": "ActiveSkillMB",
            "Size": 673149
        },
        "AppVersionMB": {
            "Hash": "c2e146d6ac26f993245ca29bc85074e2",
            "Name": "AppVersionMB",
            "Size": 358
        },
        "AutoBattleEnemyMB": {
            "Hash": "2482d74cc4b6546fd035ed667b23fdbc",
            "Name": "AutoBattleEnemyMB",
            "Size": 11135672
        },
        "BattleScheduleMB": {
            "Hash": "70534bfdfd263c2c52dc38733a6d1d7f",
            "Name": "BattleScheduleMB",
            "Size": 5086
        },
        "BattleSkillCharacterSettingMB": {
            "Hash": "71804ea4facd217987943ee183ad1cd2",
            "Name": "BattleSkillCharacterSettingMB",
            "Size": 5295
        },
        "BattleSkillNameSettingMB": {
            "Hash": "1db465aa03107274d9acf5912596614b",
            "Name": "BattleSkillNameSettingMB",
            "Size": 54569
        },
        "BoardRankMB": {
            "Hash": "50acb30f646173fd80ee832a82ce8acd",
            "Name": "BoardRankMB",
            "Size": 2110
        },
        "BookSortBonusFloorRewardMB": {
            "Hash": "d56d25035c129cdd2db38ccb31cd0e5a",
            "Name": "BookSortBonusFloorRewardMB",
            "Size": 2676
        },
        "BookSortEventMB": {
            "Hash": "811948c1633754ea5c2349dea392b4c7",
            "Name": "BookSortEventMB",
            "Size": 291
        },
        "BossBattleEnemyMB": {
            "Hash": "c8ef490cd8bf5ba95f0f3373e4277790",
            "Name": "BossBattleEnemyMB",
            "Size": 5945164
        },
        "BountyQuestEventMB": {
            "Hash": "9c7cd9d1ff65a2b600cf0fb0184b5612",
            "Name": "BountyQuestEventMB",
            "Size": 14146
        },
        "ChangeItemMB": {
            "Hash": "89c49edce33a370b15886f125bad75aa",
            "Name": "ChangeItemMB",
            "Size": 97744
        },
        "ChapterMB": {
            "Hash": "9f78d73c0fa9c6da48549e6e491e4015",
            "Name": "ChapterMB",
            "Size": 5564
        },
        "CharacterBoxSizeMB": {
            "Hash": "a8b8682f5ce6e644c0ce613e8e249fad",
            "Name": "CharacterBoxSizeMB",
            "Size": 2809
        },
        "CharacterCollectionLevelMB": {
            "Hash": "534a7a703d5e9cbeed627248a1c77d46",
            "Name": "CharacterCollectionLevelMB",
            "Size": 206488
        },
        "CharacterCollectionMB": {
            "Hash": "5b10d7c0ea2ecfaec8a03677c506c8df",
            "Name": "CharacterCollectionMB",
            "Size": 15414
        },
        "CharacterCollectionRewardMB": {
            "Hash": "46603d2f2c89f42defa9593b693e1ef2",
            "Name": "CharacterCollectionRewardMB",
            "Size": 4611
        },
        "CharacterDetailVoiceMB": {
            "Hash": "3b8bb796997ef6304057b1f09f4ac29b",
            "Name": "CharacterDetailVoiceMB",
            "Size": 724794
        },
        "CharacterLevelMB": {
            "Hash": "3afbab3ee63653e2b37187d446c937c5",
            "Name": "CharacterLevelMB",
            "Size": 27482
        },
        "CharacterLiveModeMB": {
            "Hash": "d3d68bcedfb279dacd35ff501ce05273",
            "Name": "CharacterLiveModeMB",
            "Size": 3189
        },
        "CharacterMB": {
            "Hash": "ecc96b6a5288e22406cdbf37a66c78ef",
            "Name": "CharacterMB",
            "Size": 68987
        },
        "CharacterPotentialCoefficientMB": {
            "Hash": "6c67af002958dfabb6a3d68697672aa0",
            "Name": "CharacterPotentialCoefficientMB",
            "Size": 6432
        },
        "CharacterPotentialMB": {
            "Hash": "6a0a8f78ff85f4aa5d734e51d1411deb",
            "Name": "CharacterPotentialMB",
            "Size": 442651
        },
        "CharacterProfileMB": {
            "Hash": "b127dde9338ff4d47b8f7452c92d5d6b",
            "Name": "CharacterProfileMB",
            "Size": 137301
        },
        "CharacterRankUpMaterialMB": {
            "Hash": "1be22e880b03ca45bc2d6977d18e7d34",
            "Name": "CharacterRankUpMaterialMB",
            "Size": 5132
        },
        "CharacterResetMB": {
            "Hash": "fc208e6e268ac4e9ce4d0c569bc90ba0",
            "Name": "CharacterResetMB",
            "Size": 3866
        },
        "CharacterStoryMB": {
            "Hash": "de598f3e875e43335517536e63fd5c68",
            "Name": "CharacterStoryMB",
            "Size": 128618
        },
        "ChatEffectKeywordMB": {
            "Hash": "5935f4254dffb0eef00aa8afdc13406a",
            "Name": "ChatEffectKeywordMB",
            "Size": 5470
        },
        "CollabMissionMB": {
            "Hash": "6f0cbddd0dd95fb6b029fa5a89711b74",
            "Name": "CollabMissionMB",
            "Size": 489
        },
        "CommunityMB": {
            "Hash": "06757a398fb4bb8eab27e895fb5ea3d4",
            "Name": "CommunityMB",
            "Size": 4663
        },
        "DeepLinkMB": {
            "Hash": "a50c3505cdc7038686d48bb9e675b147",
            "Name": "DeepLinkMB",
            "Size": 7265
        },
        "DownloadRawDataMB": {
            "Hash": "00ce7541cc7362abc0d81dd232886590",
            "Name": "DownloadRawDataMB",
            "Size": 97033
        },
        "DungeonBattleGridMB": {
            "Hash": "d1d0bb870c358c7985224e134155c50d",
            "Name": "DungeonBattleGridMB",
            "Size": 1508
        },
        "DungeonBattleGuestMB": {
            "Hash": "0b1f1827a80e7f2a609ff244e37e46af",
            "Name": "DungeonBattleGuestMB",
            "Size": 11994
        },
        "DungeonBattleRelicMB": {
            "Hash": "415677cdc984e60a34f318985ebcbd75",
            "Name": "DungeonBattleRelicMB",
            "Size": 36975
        },
        "EffectGroupMB": {
            "Hash": "b26e9b209656fae789dd067c9096f646",
            "Name": "EffectGroupMB",
            "Size": 1254687
        },
        "ElementBonusMB": {
            "Hash": "e9bf6e553b877c54fcaf45f6909340e5",
            "Name": "ElementBonusMB",
            "Size": 1480
        },
        "EquipmentCompositeMB": {
            "Hash": "5b87392421110fad6f05106f78bde1cf",
            "Name": "EquipmentCompositeMB",
            "Size": 16614
        },
        "EquipmentEvolutionMB": {
            "Hash": "a032d361242e308bc43e22d5c0773b50",
            "Name": "EquipmentEvolutionMB",
            "Size": 1005412
        },
        "EquipmentExclusiveEffectMB": {
            "Hash": "056f9cd43015332dd91ce9f790e15e98",
            "Name": "EquipmentExclusiveEffectMB",
            "Size": 126667
        },
        "EquipmentExclusiveSkillDescriptionMB": {
            "Hash": "0210df4efb620033a3fbbcb1711c93c5",
            "Name": "EquipmentExclusiveSkillDescriptionMB",
            "Size": 17270
        },
        "EquipmentForgeMB": {
            "Hash": "f63cb4e20c64145b75678f2c3970f73b",
            "Name": "EquipmentForgeMB",
            "Size": 636
        },
        "EquipmentLegendSacredTreasureMB": {
            "Hash": "d3bc815ca981d850d58b8fe7939a22dc",
            "Name": "EquipmentLegendSacredTreasureMB",
            "Size": 10950
        },
        "EquipmentMatchlessSacredTreasureMB": {
            "Hash": "c79619709504910611ff437c19b77849",
            "Name": "EquipmentMatchlessSacredTreasureMB",
            "Size": 7233
        },
        "EquipmentMB": {
            "Hash": "31dbfa4d8b49151918ab4bcdf7ceda29",
            "Name": "EquipmentMB",
            "Size": 5923083
        },
        "EquipmentReinforcementMaterialMB": {
            "Hash": "2ffc59efb4610fd359071e0188e2f31a",
            "Name": "EquipmentReinforcementMaterialMB",
            "Size": 157385
        },
        "EquipmentReinforcementParameterMB": {
            "Hash": "08a9e34118559e39cac0a005abcf0387",
            "Name": "EquipmentReinforcementParameterMB",
            "Size": 47113
        },
        "EquipmentSetMaterialBoxMB": {
            "Hash": "1fea8cf5bcaab123ff26cae84c9371e1",
            "Name": "EquipmentSetMaterialBoxMB",
            "Size": 11952
        },
        "EquipmentSetMaterialMB": {
            "Hash": "33fe6d0740774c74e0e504882b2c9cd4",
            "Name": "EquipmentSetMaterialMB",
            "Size": 177096
        },
        "EquipmentSetMB": {
            "Hash": "c6ea5f7754dc9d4c3441d2f13274eaaa",
            "Name": "EquipmentSetMB",
            "Size": 6554
        },
        "ErrorCodeMB": {
            "Hash": "085074ab3fa6536dac685a07fea95f5f",
            "Name": "ErrorCodeMB",
            "Size": 56036
        },
        "FaqListMB": {
            "Hash": "f82ad9a52d411c2b977488694dbb15de",
            "Name": "FaqListMB",
            "Size": 7553
        },
        "FriendCampaignMB": {
            "Hash": "5c7fef7b091bc50324417abdcee37925",
            "Name": "FriendCampaignMB",
            "Size": 788
        },
        "FriendMissionMB": {
            "Hash": "e0b4eb519876a899b53cc310bafa0548",
            "Name": "FriendMissionMB",
            "Size": 6085
        },
        "GachaCaseMB": {
            "Hash": "7374a1a39ebb9c1929c558356fa21763",
            "Name": "GachaCaseMB",
            "Size": 54553
        },
        "GachaCaseUiMB": {
            "Hash": "84c98319859774ffa820e41dee80b152",
            "Name": "GachaCaseUiMB",
            "Size": 449926
        },
        "GachaDestinyAddCharacterMB": {
            "Hash": "c6788b9a5c43e3fcbd4c43c22c15df8d",
            "Name": "GachaDestinyAddCharacterMB",
            "Size": 14641
        },
        "GachaSelectListMB": {
            "Hash": "d0b41aeca25e55d5a5f4ecfb7d74bfba",
            "Name": "GachaSelectListMB",
            "Size": 37846
        },
        "GlobalGvgCastleMB": {
            "Hash": "f3658568a1d613e3c56998853a67930d",
            "Name": "GlobalGvgCastleMB",
            "Size": 10000
        },
        "GuildLevelMB": {
            "Hash": "6866eef799fdd7bc19fdaf7926e0c0a2",
            "Name": "GuildLevelMB",
            "Size": 2102
        },
        "GuildMissionMB": {
            "Hash": "6d03fd1cbb63eea609cd8c59cf9b55a8",
            "Name": "GuildMissionMB",
            "Size": 846
        },
        "GuildRaidBossMB": {
            "Hash": "64c4e11974b267d03a2e229d2d0254da",
            "Name": "GuildRaidBossMB",
            "Size": 37148
        },
        "GuildRaidRewardMB": {
            "Hash": "332760f622bb03235de305b8d2a6d643",
            "Name": "GuildRaidRewardMB",
            "Size": 105212
        },
        "GuildTowerChallengeRewardMB": {
            "Hash": "e9dd1a6d7aec9a8ef65dee2beec3ea8f",
            "Name": "GuildTowerChallengeRewardMB",
            "Size": 73040
        },
        "GuildTowerEnemyMB": {
            "Hash": "d93988970af56405c1525a9455750ca5",
            "Name": "GuildTowerEnemyMB",
            "Size": 2426422
        },
        "GuildTowerEventMB": {
            "Hash": "282dc8b3989aa9ea843f276a72256877",
            "Name": "GuildTowerEventMB",
            "Size": 4986
        },
        "GuildTowerFloorMB": {
            "Hash": "e4ac87b2b2f9906037358a86fb489622",
            "Name": "GuildTowerFloorMB",
            "Size": 205370
        },
        "GuildTowerReinforcementJobLevelMB": {
            "Hash": "d7d56831396d9f48c5acf99e5f86fea8",
            "Name": "GuildTowerReinforcementJobLevelMB",
            "Size": 146358
        },
        "HelpMB": {
            "Hash": "657fcb13d43ee64b1fa3338faa5bc639",
            "Name": "HelpMB",
            "Size": 27401
        },
        "InquiryButtonMB": {
            "Hash": "95c04f3e30c618ea9b5aea13162801a0",
            "Name": "InquiryButtonMB",
            "Size": 2192
        },
        "ItemMaxCountSwitchingQuestMB": {
            "Hash": "01afc4da7b2df0dd9159a45c7cfd9fdf",
            "Name": "ItemMaxCountSwitchingQuestMB",
            "Size": 2327
        },
        "ItemMB": {
            "Hash": "234d1ce48a8b26d85cd98ce4b7fd2938",
            "Name": "ItemMB",
            "Size": 65249
        },
        "LeadReviewMB": {
            "Hash": "83e028f348df8347e115f132b3e4d34f",
            "Name": "LeadReviewMB",
            "Size": 52
        },
        "LegendLeagueClassMB": {
            "Hash": "b02e0d031673d4e803abc4c5ad88ff34",
            "Name": "LegendLeagueClassMB",
            "Size": 647
        },
        "LevelLinkMB": {
            "Hash": "071f126ef9d0bef1b718e76780466735",
            "Name": "LevelLinkMB",
            "Size": 699538
        },
        "LimitedEventMB": {
            "Hash": "3baa92eab8ffa87797b22717dc8f14e5",
            "Name": "LimitedEventMB",
            "Size": 1244
        },
        "LimitedLoginBonusMB": {
            "Hash": "46bf059843b4ea188a25f140bfb1a097",
            "Name": "LimitedLoginBonusMB",
            "Size": 5313
        },
        "LimitedLoginBonusRewardListMB": {
            "Hash": "57ee35082df60d3120d8dfa26a5fe072",
            "Name": "LimitedLoginBonusRewardListMB",
            "Size": 9540
        },
        "LimitedLoginBonusSwitchingDailyRewardMB": {
            "Hash": "ed734e17603d421c136e7930f39a3297",
            "Name": "LimitedLoginBonusSwitchingDailyRewardMB",
            "Size": 5584
        },
        "LimitedMissionMB": {
            "Hash": "24f1ed0d10de7ad6c426c1f168f0f637",
            "Name": "LimitedMissionMB",
            "Size": 2589
        },
        "LocalGvgCastleMB": {
            "Hash": "f18738c6617ae5163fbdacfd216532fd",
            "Name": "LocalGvgCastleMB",
            "Size": 4744
        },
        "LocalPushNotificationMB": {
            "Hash": "bbc4658d394be56d733c47e3eada1c54",
            "Name": "LocalPushNotificationMB",
            "Size": 1777
        },
        "LocalRaidBannerMB": {
            "Hash": "be6a38925cd12fbea18ac1260496653a",
            "Name": "LocalRaidBannerMB",
            "Size": 4969
        },
        "LocalRaidBonusScheduleMB": {
            "Hash": "036fbfe7f56c7f8d1818e2cc25ee9cad",
            "Name": "LocalRaidBonusScheduleMB",
            "Size": 181
        },
        "LocalRaidEventScheduleMB": {
            "Hash": "94cc56501bffe511ad64d8b3f651fe8d",
            "Name": "LocalRaidEventScheduleMB",
            "Size": 2307
        },
        "LocalRaidQuestGroupMB": {
            "Hash": "ba03de84de33cd463a2efa0a6bbaa661",
            "Name": "LocalRaidQuestGroupMB",
            "Size": 341031
        },
        "LuckyChanceMB": {
            "Hash": "2ff75f8428c7be44b46f0b7ae14cf3ce",
            "Name": "LuckyChanceMB",
            "Size": 752
        },
        "MissionClearCountRewardMB": {
            "Hash": "c261960bcbb3023dcb6bd5c1cc560dec",
            "Name": "MissionClearCountRewardMB",
            "Size": 1754
        },
        "MissionGuideMB": {
            "Hash": "60d15603284ff07bce4963d7df237b47",
            "Name": "MissionGuideMB",
            "Size": 36747
        },
        "MissionMB": {
            "Hash": "9547bf1bc67b7ee8994c4bf6661a3cc3",
            "Name": "MissionMB",
            "Size": 666746
        },
        "MissionOpenContentMB": {
            "Hash": "99d8ca0e3a5833bf9984b6083e7fcda1",
            "Name": "MissionOpenContentMB",
            "Size": 3134
        },
        "MissionTabNameMB": {
            "Hash": "44ce8ed18953f777ea33347562a5c848",
            "Name": "MissionTabNameMB",
            "Size": 6256
        },
        "MonologueMB": {
            "Hash": "5c4475595a42b53026af65d5deb7bf3c",
            "Name": "MonologueMB",
            "Size": 98192
        },
        "MonthlyLoginBonusMB": {
            "Hash": "f127927f872116afeb603d16328c987c",
            "Name": "MonthlyLoginBonusMB",
            "Size": 8192
        },
        "MonthlyLoginBonusRewardListMB": {
            "Hash": "d3af7fc6f6a60ec35ec9e1b9fde2bb1d",
            "Name": "MonthlyLoginBonusRewardListMB",
            "Size": 7909
        },
        "MusicMB": {
            "Hash": "1c120c3dfc5685a3238d9304b9e73246",
            "Name": "MusicMB",
            "Size": 4914
        },
        "NewCharacterMissionMB": {
            "Hash": "c676983e27e1591f608ae88afc7ebdce",
            "Name": "NewCharacterMissionMB",
            "Size": 7054
        },
        "OpenContentMB": {
            "Hash": "b7557efbffbfb29088b0aca70b61ceda",
            "Name": "OpenContentMB",
            "Size": 21854
        },
        "PanelMB": {
            "Hash": "d45312af662c3be61df56505f1776e09",
            "Name": "PanelMB",
            "Size": 9758
        },
        "PanelMissionMB": {
            "Hash": "c3bd8f15db3650e19c90b2889ba3f372",
            "Name": "PanelMissionMB",
            "Size": 10611
        },
        "PassiveSkillMB": {
            "Hash": "1571727081bebcc6d5607faac6c1e21b",
            "Name": "PassiveSkillMB",
            "Size": 727618
        },
        "PatternSettingMB": {
            "Hash": "058b138801f364963709ed3f228b9e2c",
            "Name": "PatternSettingMB",
            "Size": 815
        },
        "PlayerRankMB": {
            "Hash": "9f7a52e67f8b3597e3d58645e9c7e4cc",
            "Name": "PlayerRankMB",
            "Size": 274796
        },
        "PopularityVoteMB": {
            "Hash": "92fdf18d7ffc67b7537f3b9caa16ff71",
            "Name": "PopularityVoteMB",
            "Size": 5908
        },
        "PvpRankingRewardMB": {
            "Hash": "656da69564146f7ec5e388064ff2f373",
            "Name": "PvpRankingRewardMB",
            "Size": 20790
        },
        "QuestMapBuildingMB": {
            "Hash": "e8729ce3b53a2768fd8300421aa5a900",
            "Name": "QuestMapBuildingMB",
            "Size": 25278
        },
        "QuestMB": {
            "Hash": "044c33dd9e2441a8e109708cbc0cee52",
            "Name": "QuestMB",
            "Size": 318283
        },
        "RequiredCurrencyMB": {
            "Hash": "7a33242ce3863ecdafd0d4240921b3ff",
            "Name": "RequiredCurrencyMB",
            "Size": 21548
        },
        "SpecialIconItemMB": {
            "Hash": "cec386d8e9936f9750b86e6ae52eca72",
            "Name": "SpecialIconItemMB",
            "Size": 267355
        },
        "SphereMB": {
            "Hash": "3768825d4fbee44fd4a61b2dca738764",
            "Name": "SphereMB",
            "Size": 77248
        },
        "StateBonusMB": {
            "Hash": "4b2a7660bb3453ffb8255e75522fcb99",
            "Name": "StateBonusMB",
            "Size": 4541
        },
        "StateMB": {
            "Hash": "1ef07dc595ecb444d76b56ded5b35ce0",
            "Name": "StateMB",
            "Size": 4387
        },
        "SteamProductPriceListMB": {
            "Hash": "9fbb6c701fdb440a5542e843f9644f89",
            "Name": "SteamProductPriceListMB",
            "Size": 14527
        },
        "StripePointMB": {
            "Hash": "3b5cd6cfeba52744b8ee7510b64962f5",
            "Name": "StripePointMB",
            "Size": 110
        },
        "TermsMB": {
            "Hash": "7eedee02a62bc773e628eeaf3e2d8fcb",
            "Name": "TermsMB",
            "Size": 3199
        },
        "TextLanguageMB": {
            "Hash": "37daa4f2187933e3f44bca33da57c56a",
            "Name": "TextLanguageMB",
            "Size": 1804
        },
        "TextResourceDeDeMB": {
            "Hash": "8090ded4117fe39035a89ecb8033a29d",
            "Name": "TextResourceDeDeMB",
            "Size": 3299352
        },
        "TextResourceEnUsMB": {
            "Hash": "500c2a812dafd6fda4555483ad093c25",
            "Name": "TextResourceEnUsMB",
            "Size": 4312508
        },
        "TextResourceEsMxMB": {
            "Hash": "71ca69f80a6e0ef7859c653e3ebde417",
            "Name": "TextResourceEsMxMB",
            "Size": 3225347
        },
        "TextResourceFrFrMB": {
            "Hash": "71215aeeae097992083c13a79a4faafa",
            "Name": "TextResourceFrFrMB",
            "Size": 3212702
        },
        "TextResourceIdIdMB": {
            "Hash": "0776623311939a8a9bc52975bf51a0f6",
            "Name": "TextResourceIdIdMB",
            "Size": 3228851
        },
        "TextResourceJaJpMB": {
            "Hash": "e67fecda7e149dc0c4f3fba21e3a5cb9",
            "Name": "TextResourceJaJpMB",
            "Size": 4440626
        },
        "TextResourceKoKrMB": {
            "Hash": "c27c8abc6295bcf2f7c7fff61a2162f9",
            "Name": "TextResourceKoKrMB",
            "Size": 4324796
        },
        "TextResourcePtBrMB": {
            "Hash": "553860873a1f9ddb47df2dea669f1128",
            "Name": "TextResourcePtBrMB",
            "Size": 3190353
        },
        "TextResourceRuRuMB": {
            "Hash": "49becdae1f980b093fb9074e8fa307af",
            "Name": "TextResourceRuRuMB",
            "Size": 3971394
        },
        "TextResourceThThMB": {
            "Hash": "27fc87864f5ec67631847fc3308330bf",
            "Name": "TextResourceThThMB",
            "Size": 4828098
        },
        "TextResourceViVnMB": {
            "Hash": "3feec989dfce3b8b97d1ad88efcbc221",
            "Name": "TextResourceViVnMB",
            "Size": 3600334
        },
        "TextResourceZhCnMB": {
            "Hash": "54cac088b7cfe27d92f7c52894687726",
            "Name": "TextResourceZhCnMB",
            "Size": 3926156
        },
        "TextResourceZhTwMB": {
            "Hash": "3341886d6bc7aa41a395e34ce659a03c",
            "Name": "TextResourceZhTwMB",
            "Size": 3920407
        },
        "TimeServerMB": {
            "Hash": "b89f011a66251615978289ef3efb9d4a",
            "Name": "TimeServerMB",
            "Size": 1398
        },
        "TipMB": {
            "Hash": "ecb005cbc08da72af441c5fedd581216",
            "Name": "TipMB",
            "Size": 1477
        },
        "TotalActivityMedalRewardMB": {
            "Hash": "5fa0351add327256bcf9217c8ab38d64",
            "Name": "TotalActivityMedalRewardMB",
            "Size": 12927
        },
        "TowerBattleEnemyMB": {
            "Hash": "c7d87ce5345820eaf95259a7c177f4bd",
            "Name": "TowerBattleEnemyMB",
            "Size": 28999802
        },
        "TowerBattleQuestMB": {
            "Hash": "5b97ec23ccb0e45261b2d5a815bce942",
            "Name": "TowerBattleQuestMB",
            "Size": 1891676
        },
        "TradeShopSphereMB": {
            "Hash": "5afc70d62906311a1cf81940d2a62fb3",
            "Name": "TradeShopSphereMB",
            "Size": 1083
        },
        "TradeShopTabMB": {
            "Hash": "24c6ce944401e57198b01c4d742e88b3",
            "Name": "TradeShopTabMB",
            "Size": 111176
        },
        "TreasureChestCeilingMB": {
            "Hash": "9261f7876b178ce3055e3e0672156e64",
            "Name": "TreasureChestCeilingMB",
            "Size": 57
        },
        "TreasureChestItemMB": {
            "Hash": "72bc28b10fb09f4bc007f378a93647c9",
            "Name": "TreasureChestItemMB",
            "Size": 31609
        },
        "TreasureChestMB": {
            "Hash": "899a60ed5a04264c32e1d6d9ec2a1f99",
            "Name": "TreasureChestMB",
            "Size": 46992
        },
        "TutorialDescriptionMB": {
            "Hash": "068971ea241887367c05806fe25022bf",
            "Name": "TutorialDescriptionMB",
            "Size": 13389
        },
        "TutorialTextBoxMB": {
            "Hash": "4b7eb8eb290ab7e84fb12238288f0e8a",
            "Name": "TutorialTextBoxMB",
            "Size": 39894
        },
        "VipMB": {
            "Hash": "82c2a5895090f779e250746db0bdfb43",
            "Name": "VipMB",
            "Size": 17311
        },
        "WorldGroupMB": {
            "Hash": "de792d705dbb288886c196a7f08fb759",
            "Name": "WorldGroupMB",
            "Size": 66896
        }
    }
}